LICENSE
MANIFEST.in
README.rst
setup.py
DARtTool/__init__.py
DARtTool.egg-info/PKG-INFO
DARtTool.egg-info/SOURCES.txt
DARtTool.egg-info/dependency_links.txt
DARtTool.egg-info/requires.txt
DARtTool.egg-info/top_level.txt