Metadata-Version: 2.1
Name: DARtTool
Version: 0.0.2
Summary: A tool to estimate Instantaneous Reproduction Number(Rt) for the pandemic
Home-page: https://github.com/Kerr93/DARt/tree/master/DARt
Author: Xian Yang, Shuo Wang, Yuting Xing, Ling Li, Richard Yi Da Xu, Karl J.Friston and Yike Guo
Author-email: y.xing19@imperial.ac.uk
License: UNKNOWN
Platform: UNKNOWN
Classifier: Programming Language :: Python :: 3
Classifier: License :: OSI Approved :: MIT License
Classifier: Operating System :: OS Independent
